{"scores": [{"rank": 0, "playerId": "H0bYaUD6BsdB2zJcDRUvFSgsBv3p", "playerName": "Supreme.Worm#56880", "score": 18}, {"rank": 1, "playerId": "vMvvD5lQwxbz3IsKKhV3y9CBytZJ", "playerName": "DSallee#28773", "score": 18}, {"rank": 2, "playerId": "X93mdBPcXeMrcteTBsKN8xFy4g1d", "playerName": "I.am.Azwell#69332", "score": 19}, {"rank": 3, "playerId": "jKKZvIhMPJJZALLzgxwUZlCWs7C5", "playerName": "dbomb21q#90650", "score": 22}, {"rank": 4, "playerId": "P1lVWXuT1AGeCCeNQnjD5ctkPrTJ", "playerName": "ShortDogg559#59164", "score": 23}, {"rank": 5, "playerId": "WOdqkNFNhz2UcRLBXaw4Q0sB0a3r", "playerName": "FlawlessMari#83444", "score": 23}, {"rank": 6, "playerId": "1FYfF5CjQAHOwqvLQ5Yk6OWDRRqg", "playerName": "Graylocke250#60045", "score": 24}, {"rank": 7, "playerId": "EET5PBzzRWLdHGPVOJVq3bqUGPuX", "playerName": "Thyrial#88665", "score": 24}, {"rank": 8, "playerId": "e0D8mgZ110SaIgLPDjYajoVkJMvg", "playerName": "MrJoneser#46126", "score": 24}, {"rank": 9, "playerId": "lIQMdvOsZpAFCnUIaAFFdiJ8rlHN", "playerName": "melodyutley0709#57392", "score": 24}, {"rank": 10, "playerId": "rB3bBjSfQel0OJGysyFCBMnhvx3U", "playerName": "werdna.sev#95683", "score": 25}, {"rank": 11, "playerId": "dUxFcxrvcuWKiYDTZLD4LTzHhhvp", "playerName": "pa4kourpro#35742", "score": 26}, {"rank": 12, "playerId": "RF9TyYTx42n7zzHvTprLAE2EZ4R1", "playerName": "kruegermichael#20085", "score": 27}, {"rank": 13, "playerId": "Af2KPZ0vrv9N8Go0hIL5QwCydWlf", "playerName": "ZNUTZ619#13505", "score": 28}, {"rank": 14, "playerId": "rA6lIHeh8Bcqeon2WcNgOXT0zNmp", "playerName": "spanklovich#89619", "score": 29}, {"rank": 15, "playerId": "s0xmEL4NRbgrBTKW5HVh9zKxxfPs", "playerName": "SkeeterArnold#23863", "score": 29}, {"rank": 16, "playerId": "8ulwHqMYqHIastRtfifLjPPYCga2", "playerName": "Still_life#26504", "score": 31}, {"rank": 17, "playerId": "DFjt6d66q6vwPO66DQLxvpCpcpgS", "playerName": "iamthisis#39503", "score": 31}, {"rank": 18, "playerId": "SNxnaGhTPmy1FqiyYHoil2G78o4m", "playerName": "DaFeeeesh#20195", "score": 31}, {"rank": 19, "playerId": "SoWSL1eWwotTrvHFKqlRmJCiy1f0", "playerName": "vpagliai0145#77677", "score": 31}, {"rank": 20, "playerId": "j6JZ32VeNXxghxJQyM08N1NTuo79", "playerName": "Terrysdrawoff#12120", "score": 31}, {"rank": 21, "playerId": "u2oUNUwQiCONOJXzYXij85Bt3wJj", "playerName": "anconeus529#79605", "score": 31}, {"rank": 22, "playerId": "bwPBJ7xS1ooJittbwlI0pQHKnUTc", "playerName": "KregA#18899", "score": 32}, {"rank": 23, "playerId": "dQwnWfy0wuT2h79DZBkF4ByqjQfc", "playerName": "Jackieboy2323#61005", "score": 32}, {"rank": 24, "playerId": "t0qUJLWvlWYd9b5f1zdrDCP8BmIP", "playerName": "cxzyyt4#19710", "score": 32}, {"rank": 25, "playerId": "xFkzmBUvOMWI6uYsVkozedXl3vxR", "playerName": "Colby_Shiehsty#33257", "score": 32}, {"rank": 26, "playerId": "8ecZyvmzr4AHZ1j50eZEuon4qyk9", "playerName": "glasha7262#73241", "score": 33}, {"rank": 27, "playerId": "JDH976aJOTJ5KRgmh77a9By6EqMu", "playerName": "PuckLuckMN#95618", "score": 33}, {"rank": 28, "playerId": "crS8PVficnfCRJPRqFIUqhQ3Ic1A", "playerName": "RandyDecker24#93345", "score": 33}, {"rank": 29, "playerId": "gxDcWRKcpq4FS3Nc7aXlQhb25aE8", "playerName": "jaguar.224698#67632", "score": 33}, {"rank": 30, "playerId": "GZBMvxqw6Ii5wJrlkQ448MSGatv1", "playerName": "Skadam75#54237", "score": 34}, {"rank": 31, "playerId": "d0SR6wxsbm5ud72Ee0xwRRRcMBUF", "playerName": "PangMeta#50340", "score": 34}, {"rank": 32, "playerId": "4FqYDu769uwG8gahlEj7sIjRz4qu", "playerName": "HDStevo#80550", "score": 35}, {"rank": 33, "playerId": "7Ja3KlgUYusHCNk94dRZXj7HYbWk", "playerName": "azumax3988#99399", "score": 35}, {"rank": 34, "playerId": "p6K00JTk3fKdbx2WyfPZR34TSsIF", "playerName": "Bragg14#91229", "score": 35}, {"rank": 35, "playerId": "nCqaGSK1Lb0LJc9ki4cscrmJINdk", "playerName": "llandishjq#36890", "score": 36}, {"rank": 36, "playerId": "bejaEQKraYqMYovOKukN8aMcDlDw", "playerName": "Moontrain74#45308", "score": 37}, {"rank": 37, "playerId": "ojoVg3hXMBkrXSRLtSv8Z04aKO4U", "playerName": "wesbomb34#76680", "score": 37}, {"rank": 38, "playerId": "wVIqAauQnv6Mhpv9g2f0xSfI1Bhw", "playerName": "Captain_T2010#20484", "score": 37}, {"rank": 39, "playerId": "6ZTdCA1XrMCUtgUqG18p4oRMZy0T", "playerName": "barteqx8#10692", "score": 38}, {"rank": 40, "playerId": "ZRSuHLcCml754nq8BVN7EwE8CgxB", "playerName": "PricklySalmon3251#97759", "score": 38}, {"rank": 41, "playerId": "fhiwupN1to0n8UJuAFNSRMXqNTEl", "playerName": "cloudniner#70219", "score": 40}, {"rank": 42, "playerId": "bpjnmav5KvxehPKbuoTUXR5KS8S3", "playerName": "IchBinBob#40854", "score": 41}, {"rank": 43, "playerId": "uC4D5KnQWEQgXMfCMaBIIpim8184", "playerName": "Possutohveli#74838", "score": 41}, {"rank": 44, "playerId": "qMVsFCvJQSIm1sUxboLRxsbGeMvR", "playerName": "EZECK21#70726", "score": 43}, {"rank": 45, "playerId": "KS2lmcJTtYrIjmPyPadDM18k3EyM", "playerName": "Romines1993#89526", "score": 44}, {"rank": 46, "playerId": "kNjwpK7hhdbLjXwDbidpV9FLVmQ5", "playerName": "TheComets#44157", "score": 44}, {"rank": 47, "playerId": "5b4Rnn9HNMLQHQzlumlhlCrSCJJa", "playerName": "jjack14#29924", "score": 47}, {"rank": 48, "playerId": "fLLYyCdr1TbUq2uSsRDzuAVAziY4", "playerName": "magaman.2026#83973", "score": 47}, {"rank": 49, "playerId": "hqQWcpBOpF8L4W9GooQpQQE8Uqqi", "playerName": "brucifer616#65280", "score": 47}, {"rank": 50, "playerId": "PuCoJ7nm5klmNGwy2uUSRyVTq6d0", "playerName": "travisscott100#68222", "score": 49}, {"rank": 51, "playerId": "sLZONGb7MlX5F4TWq6d1FOKc2I2l", "playerName": "BigMike8797#48979", "score": 51}, {"rank": 52, "playerId": "87XrfVCmdsqEkDLKF6QOWRKojHRW", "playerName": "Hightowers007#48276", "score": 52}, {"rank": 53, "playerId": "LNsWObfeYts57ZGFtQ2vKqGBAbJu", "playerName": "Kazzyed_0707#41563", "score": 56}, {"rank": 54, "playerId": "NPrXcT5Hb2Gq5fm2VkkRrjIGltDc", "playerName": "ty.dummy#20595", "score": 69}, {"rank": 55, "playerId": "3rSAptBuTd8ajBWoPlyJBzybNunj", "playerName": "WaylonDaGoat2024#79126", "score": 90}], "ranks": [1, 1, 3, 4, 5, 5, 7, 7, 7, 7, 11, 12, 13, 14, 15, 15, 17, 17, 17, 17, 17, 17, 23, 23, 23, 23, 27, 27, 27, 27, 31, 31, 33, 33, 33, 36, 37, 37, 37, 40, 40, 42, 43, 43, 45, 46, 46, 48, 48, 48, 51, 52, 53, 54, 55, 56], "total": 56, "seed": 2699}