{"scores": [{"rank": 0, "playerId": "dl1zp496A3GYPiMwqzJ1B1q4nWd3", "playerName": "AZZ.well.derrp#4163", "score": 14}, {"rank": 1, "playerId": "VFU9x9yWcaKLs4t14uAtKUJwlCX2", "playerName": "SillyFox3203#5587", "score": 16}, {"rank": 2, "playerId": "a6KzJ9ai1aQn78MsuViXmxq3OcpK", "playerName": "Buckeye4Truth#6819", "score": 17}, {"rank": 3, "playerId": "X93mdBPcXeMrcteTBsKN8xFy4g1d", "playerName": "I.am.Azwell#1927", "score": 18}, {"rank": 4, "playerId": "3WNAkInlksoNY3REedSwBsxP6V86", "playerName": "lopdog301#4012", "score": 22}, {"rank": 5, "playerId": "dV2umaIMQEnZbuS7CrYl2rykILv4", "playerName": "Westcliff123#8195", "score": 22}, {"rank": 6, "playerId": "arSKPeK35aspHv5IVUPKDMBF489D", "playerName": "DeGreuter#5687", "score": 24}, {"rank": 7, "playerId": "X99yGNOJb9Xr16cTPm52IZlsROXm", "playerName": "l.o0.0o.l#6864", "score": 25}, {"rank": 8, "playerId": "oJWMhjEcriNwu2DpcnbJfDOuOlom", "playerName": "st_ereo_963#6734", "score": 25}, {"rank": 9, "playerId": "3eqH9CiX1sCWSsR9buiMS3NDxaLt", "playerName": "stinkybulldog#4940", "score": 27}, {"rank": 10, "playerId": "EMpnAYyqkCFnSVPRmHYgRwyFuhJm", "playerName": "CrazyLeonMax#4194", "score": 27}, {"rank": 11, "playerId": "fSletFtTEIzuY9qH9NGafJnr3OL4", "playerName": "JulianIsAweenie#6844", "score": 27}, {"rank": 12, "playerId": "zLH4Lwm75JzJr3Il2mn62kFnLb8y", "playerName": "Discgolfer1#5448", "score": 27}, {"rank": 13, "playerId": "4LR3fln0JjJclp1QkgYoTCZi7TGv", "playerName": "ryant.2331#5763", "score": 28}, {"rank": 14, "playerId": "JGwjOvugc9WBxThPGoMvlVZ1hAq8", "playerName": "MamuPamu#8203", "score": 28}, {"rank": 15, "playerId": "UwsQcukQ8WJcZMmFdXwxvSUVOgB9", "playerName": "Bryodell2989#1921", "score": 29}, {"rank": 16, "playerId": "LCHnk3ZrR8vWJtIafKu1oRu2wSU5", "playerName": "kev.kerr.44#7006", "score": 30}, {"rank": 17, "playerId": "U2paQhT5Lk2xNvJFoa43CvulOPf1", "playerName": "AdolfRizzler6741#4343", "score": 30}, {"rank": 18, "playerId": "b2x7NlxBR87Qo7Bopsi0cyxfzG0i", "playerName": "WingmanJoel#2748", "score": 30}, {"rank": 19, "playerId": "2IvsTzij4V8GqdWS1KyQOAwkWD7N", "playerName": "RaiensLAT#7735", "score": 31}, {"rank": 20, "playerId": "4CHhxuEtlMm7t7OfMBMCIlJVlt1H", "playerName": "TonyMontana55#5211", "score": 31}, {"rank": 21, "playerId": "E5VMldWVYlYSnFYiHcgZMV0jimLs", "playerName": "Used_Napkin#4793", "score": 31}, {"rank": 22, "playerId": "WOdqkNFNhz2UcRLBXaw4Q0sB0a3r", "playerName": "FlawlessMari#1000", "score": 31}, {"rank": 23, "playerId": "8TL3c0r0m4EtkQ7ygIzHS28mczgH", "playerName": "Thewhitemacho#1631", "score": 32}, {"rank": 24, "playerId": "imJV4NcOzrQLxdU6q3TR0HikfCNK", "playerName": "TravieG81#6799", "score": 36}, {"rank": 25, "playerId": "bpjnmav5KvxehPKbuoTUXR5KS8S3", "playerName": "IchBinBob#5484", "score": 37}, {"rank": 26, "playerId": "BhjVbBxUBLzZuCXUWBGF5K0kRVBc", "playerName": "Recless#2823", "score": 38}, {"rank": 27, "playerId": "ON4k6FqonKfYyPvxTsuuH1kC30Gv", "playerName": "J2daroche#1926", "score": 38}, {"rank": 28, "playerId": "nlSbqvz4gJKZgzZ2L7BXbW2NWRZJ", "playerName": "LynxLynx007#5547", "score": 38}, {"rank": 29, "playerId": "ekzubV5ffFVa1rskM84EjSur6GVL", "playerName": "Fraze71#6670", "score": 39}, {"rank": 30, "playerId": "whnm07RLsvghZv3om9pfSjMZ4twh", "playerName": "lilfat1999.2023#9310", "score": 39}, {"rank": 31, "playerId": "1sc4qowsQAOUHoMxgZeRMIGVZ5FD", "playerName": "Jaman_897#8166", "score": 40}, {"rank": 32, "playerId": "tjvH2dxZaNRJx5Lsi61oNVAZvWLz", "playerName": "mcamero#4276", "score": 40}, {"rank": 33, "playerId": "CrBT2oxfffwoLmojQmevf0B6QUyn", "playerName": "DaTwin2n2#5704", "score": 54}, {"rank": 34, "playerId": "3qSNJ030iDAMvtG2PsHEqOLyvgOy", "playerName": "igor2013ck#4923", "score": 60}, {"rank": 35, "playerId": "43tu99M3E6YKUfVlWxsWY7LKRVkb", "playerName": "Ryry1218#6318", "score": 66}, {"rank": 36, "playerId": "hUbtjmgh4MtFzKtPwbG9j7GhJ8Cz", "playerName": "Chuckie48#8180", "score": 70}, {"rank": 37, "playerId": "7rhDdTwmFxMX61hAteums1ftU6aW", "playerName": "lemondbiker#1816", "score": 89}, {"rank": 38, "playerId": "VV0CiNsDptmLxJ2amgdMbtEgGils", "playerName": "Direct_shadower1#2311", "score": 100}], "ranks": [1, 2, 3, 4, 5, 5, 7, 8, 8, 10, 10, 10, 10, 14, 14, 16, 17, 17, 17, 20, 20, 20, 20, 24, 25, 26, 27, 27, 27, 30, 30, 32, 32, 34, 35, 36, 37, 38, 39], "total": 39, "seed": 6481}